emailprotectionslib/Resolver.py
emailprotectionslib/__init__.py
emailprotectionslib/dmarc.py
emailprotectionslib/spf.py
py_emailprotections-0.8.5.dist-info/LICENSE
py_emailprotections-0.8.5.dist-info/METADATA
py_emailprotections-0.8.5.dist-info/WHEEL
py_emailprotections-0.8.5.dist-info/top_level.txt
py_emailprotections-0.8.5.dist-info/RECORD
