Metadata-Version: 2.1
Name: py-emailprotections
Version: 0.8.5
Summary: Python library to interact with SPF and DMARC
Home-page: https://github.com/poipoii/pyemailprotectionslib
Author: poipoii
Author-email: earth.sama@gmail.com
License: UNKNOWN
Platform: UNKNOWN
Classifier: Development Status :: 1 - Planning
Classifier: Environment :: Plugins
Classifier: Intended Audience :: Developers
Classifier: Operating System :: OS Independent
Classifier: Programming Language :: Python
Classifier: Programming Language :: Python :: 2
Classifier: Programming Language :: Python :: 3
Classifier: License :: OSI Approved :: MIT License
